cron_descriptor/CasingTypeEnum.py
cron_descriptor/DescriptionTypeEnum.py
cron_descriptor/Exception.py
cron_descriptor/ExpressionDescriptor.py
cron_descriptor/ExpressionParser.py
cron_descriptor/GetText.py
cron_descriptor/Options.py
cron_descriptor/StringBuilder.py
cron_descriptor/__init__.py
cron_descriptor/__main__.py
cron_descriptor/locale/cs_CZ.mo
cron_descriptor/locale/de_DE.mo
cron_descriptor/locale/en_US.mo
cron_descriptor/locale/es_ES.mo
cron_descriptor/locale/fa_IR.mo
cron_descriptor/locale/fr_FR.mo
cron_descriptor/locale/it_IT.mo
cron_descriptor/locale/ja_JP.mo
cron_descriptor/locale/ko_KR.mo
cron_descriptor/locale/nb_NO.mo
cron_descriptor/locale/nl_NL.mo
cron_descriptor/locale/pt_PT.mo
cron_descriptor/locale/ru_RU.mo
cron_descriptor/locale/sk_SK.mo
cron_descriptor/locale/sv_SE.mo
cron_descriptor/locale/ta_IN.mo
cron_descriptor/locale/tr_TR.mo
cron_descriptor/locale/uk_UA.mo
cron_descriptor/locale/vi_VN.mo
cron_descriptor/locale/zh_CN.mo
cron_descriptor-1.4.5.dist-info/LICENSE
cron_descriptor-1.4.5.dist-info/METADATA
cron_descriptor-1.4.5.dist-info/WHEEL
cron_descriptor-1.4.5.dist-info/top_level.txt
cron_descriptor-1.4.5.dist-info/RECORD
