Metadata-Version: 2.1
Name: cron_descriptor
Version: 1.4.5
Summary: A Python library that converts cron expressions into human readable strings.
Home-page: https://github.com/Salamek/cron-descriptor
Author: Adam Schubert
Author-email: adam.schubert@sg1-game.net
Classifier: Development Status :: 5 - Production/Stable
Classifier: Environment :: Web Environment
Classifier: Environment :: Console
Classifier: Intended Audience :: Developers
Classifier: License :: OSI Approved :: MIT License
Classifier: Operating System :: OS Independent
Classifier: Programming Language :: Python
Classifier: Programming Language :: Python :: 3.8
Classifier: Programming Language :: Python :: 3.9
Classifier: Programming Language :: Python :: 3.10
Classifier: Programming Language :: Python :: 3.11
Classifier: Programming Language :: Python :: 3.12
Classifier: Topic :: Software Development
Provides-Extra: dev
License-File: LICENSE
